nomos/__init__.py
nomos/cli.py
nomos/client.py
nomos/config.py
nomos/constants.py
nomos/core.py
nomos/py.typed
nomos/server.py
nomos/state_machine.py
nomos/types.py
nomos/api/__init__.py
nomos/api/agent.py
nomos/api/app.py
nomos/api/db.py
nomos/api/models.py
nomos/api/security.py
nomos/api/sessions.py
nomos/api/static/index.html
nomos/api/tools/__init__.py
nomos/events/__init__.py
nomos/events/emitter.py
nomos/events/models.py
nomos/llms/__init__.py
nomos/llms/anthropic.py
nomos/llms/base.py
nomos/llms/cohere.py
nomos/llms/google.py
nomos/llms/groq.py
nomos/llms/huggingface.py
nomos/llms/mistral.py
nomos/llms/ollama.py
nomos/llms/openai.py
nomos/memory/__init__.py
nomos/memory/base.py
nomos/memory/flow.py
nomos/memory/summary.py
nomos/models/__init__.py
nomos/models/agent.py
nomos/models/flow.py
nomos/models/session.py
nomos/models/tool.py
nomos/sessions/__init__.py
nomos/sessions/base.py
nomos/sessions/default.py
nomos/sessions/prod.py
nomos/testing/__init__.py
nomos/testing/e2e.py
nomos/testing/yaml_runner.py
nomos/testing/yaml_tests.py
nomos/tools/api.py
nomos/tools/mcp.py
nomos/tools/models.py
nomos/utils/__init__.py
nomos/utils/flow_utils.py
nomos/utils/generator.py
nomos/utils/logging.py
nomos/utils/misc.py
nomos/utils/tracing.py
nomos/utils/utils.py
nomos/utils/yml2mm.py
nomos-0.3.7.dist-info/METADATA
nomos-0.3.7.dist-info/WHEEL
nomos-0.3.7.dist-info/entry_points.txt
nomos-0.3.7.dist-info/RECORD
