Metadata-Version: 2.4
Name: nomos
Version: 0.3.7
Summary: Configurable multi-step agent framework for building advanced LLM-powered assistants
Author-email: chandralegend <irugalbandarachandra@gmail.com>
License: MIT
Requires-Python: <4.0,>=3.10
Requires-Dist: colorama<0.5.0,>=0.4.6
Requires-Dist: docstring-parser<0.17,>=0.16
Requires-Dist: greenlet>=3.2.3
Requires-Dist: httpx>=0.28.1
Requires-Dist: loguru<0.8.0,>=0.7.3
Requires-Dist: numpy>=2.2.6
Requires-Dist: pydantic-settings<3.0.0,>=2.9.1
Requires-Dist: pydantic<3.0.0,>=2.11.3
Requires-Dist: pyyaml<7.0.0,>=6.0.2
Provides-Extra: anthropic
Requires-Dist: anthropic<0.56.0,>=0.55.0; extra == 'anthropic'
Provides-Extra: cli
Requires-Dist: rich<14.0.0,>=13.0.0; extra == 'cli'
Requires-Dist: typer<0.17.0,>=0.16.0; extra == 'cli'
Provides-Extra: cohere
Requires-Dist: cohere>=5.16.1; extra == 'cohere'
Provides-Extra: google
Requires-Dist: google-genai<2.0.0,>=1.12.1; extra == 'google'
Provides-Extra: groq
Requires-Dist: groq>=0.29.0; extra == 'groq'
Requires-Dist: instructor>=1.9.2; extra == 'groq'
Provides-Extra: huggingface
Requires-Dist: huggingface-hub>=0.32.0; extra == 'huggingface'
Provides-Extra: mcp
Requires-Dist: fastmcp>=2.7.1; extra == 'mcp'
Provides-Extra: mistralai
Requires-Dist: instructor>=1.9.2; extra == 'mistralai'
Requires-Dist: mistralai<2.0.0,>=1.7.0; extra == 'mistralai'
Provides-Extra: ollama
Requires-Dist: ollama>=0.5.1; extra == 'ollama'
Provides-Extra: openai
Requires-Dist: openai<2.0.0,>=1.76.0; extra == 'openai'
Requires-Dist: tiktoken<0.10.0,>=0.9.0; extra == 'openai'
Provides-Extra: serve
Requires-Dist: asyncpg<0.31.0,>=0.30.0; extra == 'serve'
Requires-Dist: fastapi-limiter>=0.1.6; extra == 'serve'
Requires-Dist: fastapi<0.116.0,>=0.115.12; extra == 'serve'
Requires-Dist: kafka-python>=2.2.15; extra == 'serve'
Requires-Dist: psycopg2-binary<3.0.0,>=2.9.10; extra == 'serve'
Requires-Dist: pyjwt>=2.10.1; extra == 'serve'
Requires-Dist: redis<7.0.0,>=6.2.0; extra == 'serve'
Requires-Dist: sqlmodel<0.0.25,>=0.0.24; extra == 'serve'
Requires-Dist: starlette-csrf>=3.0.0; extra == 'serve'
Requires-Dist: uvicorn<0.35.0,>=0.34.3; extra == 'serve'
Provides-Extra: traces
Requires-Dist: opentelemetry-api<2.0.0,>=1.33.0; extra == 'traces'
Requires-Dist: opentelemetry-exporter-otlp<2.0.0,>=1.33.0; extra == 'traces'
Requires-Dist: opentelemetry-instrumentation<0.55,>=0.54b0; extra == 'traces'
Requires-Dist: opentelemetry-sdk<2.0.0,>=1.33.0; extra == 'traces'
